[
  {
    "id": "bootstrap",
    "label": "Bootstrap",
    "items": [
      {
        "id": "bootstrap_menus",
        "label": "Menus",
        "items": [
          { "href": "/examples/Bootstrap/DropDown", "label": "Drop down" },
          { "href": "/examples/Bootstrap/Navbar", "label": "Navbar" },
          { "href": "/examples/Bootstrap/Nav", "label": "Nav" },
          { "href": "/examples/Bootstrap/ItemVariants", "label": "Item Variants" },
          { "href": "/examples/Bootstrap/Tabs", "label": "Tabs" },
          { "href": "/examples/Bootstrap/Pagination", "label": "Pagination" },
          { "href": "/examples/Bootstrap/Breadcrumbs", "label": "Breadcrumbs" },
          { "href": "/examples/Bootstrap/Sidebar", "label": "Sidebar" }
        ]
      },
      {
        "id": "bootstrap_menus2",
        "label": "Menus",
        "items": [
          { "href": "/examples/Bootstrap/DropDown", "label": "Drop down" },
          { "href": "/examples/Bootstrap/Navbar", "label": "Navbar" },
          { "href": "/examples/Bootstrap/Nav", "label": "Nav" },
          { "href": "/examples/Bootstrap/ItemVariants", "label": "Item Variants" },
          { "href": "/examples/Bootstrap/Tabs", "label": "Tabs" },
          { "href": "/examples/Bootstrap/Pagination", "label": "Pagination" },
          { "href": "/examples/Bootstrap/Breadcrumbs", "label": "Breadcrumbs" },
          { "href": "/examples/Bootstrap/Sidebar", "label": "Sidebar" }
        ]
      }
    ]
  },
  {
    "id": "views",
    "label": "Views",
    "items": [
      { "href": "/examples/Collapsible/Collapsible", "label": "Collapsible" },
      { "href": "/examples/Json2Html/FormTest", "label": "Json2Html" },
      { "href": "/examples/DataGrid/Demo", "label": "Data Grid" },
      { "href": "/examples/Calendar/Demo", "label": "Calendar" },
      { "href": "/examples/Charts/Demo", "label": "Charts" }
    ]
  },
  {
    "id": "forms",
    "label": "Forms",
    "items": [
      { "href": "/examples/DisplayForm/AllTypes", "label": "All Field Types" },
      { "href": "/examples/DisplayForm/ContactUs", "label": "Contact Us" },
      { "href": "/examples/DisplayForm/Login", "label": "Login" },
      { "href": "/examples/DisplayForm/Registration", "label": "Registration" },
      { "href": "/examples/DisplayForm/Survey", "label": "Survey" },
      { "href": "/examples/DisplayForm/Newsletter", "label": "Newsletter Sign-up" },
      { "href": "/examples/DisplayForm/Payment", "label": "Payment" },
      { "href": "/examples/DisplayForm/FileUpload", "label": "File Upload" },
      { "href": "/examples/DisplayForm/Feedback", "label": "Feedback" },
      { "href": "/examples/DisplayForm/Comment", "label": "Comment" },
      { "href": "/examples/DisplayForm/RSVP", "label": "RSVP" },
      { "href": "/examples/DisplayForm/PasswordReset", "label": "Password Reset" },
      { "href": "/examples/DisplayForm/SubscriptionCancellation", "label": "Subscription Cancellation" }
    ]
  },
  {
    "id": "icons",
    "label": "Icons",
    "items": [
      { "href": "/icons/FontAwesome", "label": "Font Awesome" }
    ]
  }
]